Products.ZopeVersionControl-4.1-py3.11-nspkg.pth
Products/ZopeVersionControl/EventLog.py
Products/ZopeVersionControl/Repository.py
Products/ZopeVersionControl/SequenceWrapper.py
Products/ZopeVersionControl/Utility.py
Products/ZopeVersionControl/Version.py
Products/ZopeVersionControl/VersionHistory.py
Products/ZopeVersionControl/VersionSupport.py
Products/ZopeVersionControl/ZopeRepository.py
Products/ZopeVersionControl/ZopeVersion.py
Products/ZopeVersionControl/ZopeVersionHistory.py
Products/ZopeVersionControl/__init__.py
Products/ZopeVersionControl/interfaces.py
Products/ZopeVersionControl/issues.txt
Products/ZopeVersionControl/nonversioned.py
Products/ZopeVersionControl/dtml/RepositoryAddForm.dtml
Products/ZopeVersionControl/dtml/RepositoryManageMain.dtml
Products/ZopeVersionControl/dtml/RepositoryProperties.dtml
Products/ZopeVersionControl/dtml/VersionControlLog.dtml
Products/ZopeVersionControl/dtml/VersionControlMain.dtml
Products/ZopeVersionControl/dtml/VersionHistoryManageMain.dtml
Products/ZopeVersionControl/dtml/VersionHistoryProperties.dtml
Products/ZopeVersionControl/dtml/VersionManageMain.dtml
Products/ZopeVersionControl/dtml/VersionProperties.dtml
Products/ZopeVersionControl/help/Repository-Add.stx
Products/ZopeVersionControl/help/Repository-Manage.stx
Products/ZopeVersionControl/help/Repository-Properties.stx
Products/ZopeVersionControl/help/Version-Manage.stx
Products/ZopeVersionControl/help/Version-Properties.stx
Products/ZopeVersionControl/help/VersionControl.stx
Products/ZopeVersionControl/help/VersionHistory-Manage.stx
Products/ZopeVersionControl/help/VersionHistory-Properties.stx
Products/ZopeVersionControl/tests/__init__.py
Products/ZopeVersionControl/tests/common.py
Products/ZopeVersionControl/tests/testReferenceVersioning.py
Products/ZopeVersionControl/tests/testVersionControl.py
Products/ZopeVersionControl/tests/testVersionHistory.py
Products/ZopeVersionControl/tests/test_all.py
Products/ZopeVersionControl/www/Repository.gif
Products.ZopeVersionControl-4.1.dist-info/LICENSE.rst
Products.ZopeVersionControl-4.1.dist-info/METADATA
Products.ZopeVersionControl-4.1.dist-info/WHEEL
Products.ZopeVersionControl-4.1.dist-info/entry_points.txt
Products.ZopeVersionControl-4.1.dist-info/namespace_packages.txt
Products.ZopeVersionControl-4.1.dist-info/top_level.txt
Products.ZopeVersionControl-4.1.dist-info/RECORD
