Metadata-Version: 2.1
Name: Products.ZopeVersionControl
Version: 4.1
Summary: Zope Version Control
Home-page: https://github.com/zopefoundation/Products.ZopeVersionControl
Author: Zope Foundation and Contributors
Author-email: zope-dev@zope.dev
License: ZPL 2.1
Project-URL: Issue Tracker, https://github.com/zopefoundation/Products.ZopeVersionControl/issues
Project-URL: Sources, https://github.com/zopefoundation/Products.ZopeVersionControl
Keywords: version control
Classifier: Development Status :: 6 - Mature
Classifier: Framework :: Zope :: 5
Classifier: License :: OSI Approved :: Zope Public License
Classifier: Programming Language :: Python
Classifier: Programming Language :: Python :: 3.7
Classifier: Programming Language :: Python :: 3.8
Classifier: Programming Language :: Python :: 3.9
Classifier: Programming Language :: Python :: 3.10
Classifier: Programming Language :: Python :: 3.11
Classifier: Programming Language :: Python :: 3.12
Classifier: Programming Language :: Python :: Implementation :: CPython
Requires-Python: >=3.7
License-File: LICENSE.rst
Requires-Dist: setuptools
Requires-Dist: zope.interface
Requires-Dist: Acquisition
Requires-Dist: DateTime
Requires-Dist: transaction
Requires-Dist: ZODB
Requires-Dist: Zope
